{
  "id": 30,
  "title": "Dollywood's Environmental Sustainability Report Shows 40% Reduction in Single-Use Plastics",
  "author": "Kolby Johnson",
  "date": "July 25, 2025",
  "image": "/images/30.webp",
  "excerpt": "Mid-year sustainability report reveals significant environmental achievements including plastic reduction, increased recycling rates, and successful implementation of eco-friendly initiatives that position Dollywood as a leader in theme park environmental responsibility.",
  "content": "<h3>Plastic Reduction Initiative Exceeds Goals</h3><p>Dollywood's comprehensive plastic reduction program has achieved a 40% decrease in single-use plastic consumption compared to 2024 levels, surpassing initial targets through systematic replacement of disposable items with sustainable alternatives. The initiative includes biodegradable straws, reusable souvenir cups with discount refill programs, compostable food containers, and elimination of plastic bags in retail locations, demonstrating that environmental responsibility and guest convenience can coexist successfully.</p><h3>Comprehensive Recycling Program Expands</h3><p>The park's enhanced recycling infrastructure now includes over 200 clearly marked recycling stations strategically placed throughout guest areas, with color-coded bins for different materials and educational signage that helps visitors properly sort waste. Behind-the-scenes improvements include automated sorting systems, composting programs for food waste, and partnerships with local recycling facilities that ensure materials are properly processed rather than shipped to distant locations.</p><h3>Energy Conservation Measures Reduce Impact</h3><p>Sustainability efforts extend beyond waste reduction to include comprehensive energy conservation measures such as LED lighting conversions, solar panel installations on select buildings, and smart climate control systems that reduce energy consumption during off-peak hours. These initiatives have resulted in a 25% reduction in overall energy usage per guest compared to previous years, demonstrating that operational efficiency and environmental stewardship are mutually beneficial goals.</p><h3>Water Conservation Protects Regional Resources</h3><p>Advanced water conservation technologies including low-flow fixtures, smart irrigation systems, and water reclamation programs have reduced Dollywood's water consumption by 30% while maintaining the lush landscaping and water features that enhance guest experiences. The park's commitment to protecting regional water resources reflects understanding of the Great Smoky Mountains ecosystem's importance and Dollywood's responsibility as a major regional attraction.</p><h3>Environmental Leadership Inspires Industry Change</h3><p>Dollywood's transparent reporting of environmental achievements and challenges positions the park as a sustainability leader within the theme park industry, inspiring other attractions to implement similar programs. The successful integration of environmental initiatives with business operations demonstrates that sustainable practices can enhance rather than compromise guest experiences while protecting the natural beauty that draws millions of visitors to the Smoky Mountain region.</p>"
}